WuaiPojieLuntanjinghuaJi2020ErFix1/README.md
WuaiPojieLuntanjinghuaJi2020ErFix1/__init__.py
WuaiPojieLuntanjinghuaJi2020ErFix1/__main__.py
WuaiPojieLuntanjinghuaJi2020ErFix1/file.epub
WuaiPojieLuntanjinghuaJi2020ErFix1/index.html
WuaiPojieLuntanjinghuaJi2020ErFix1/css/__init__.py
WuaiPojieLuntanjinghuaJi2020ErFix1/css/annotations.css
WuaiPojieLuntanjinghuaJi2020ErFix1/css/main.css
WuaiPojieLuntanjinghuaJi2020ErFix1/css/normalize.css
WuaiPojieLuntanjinghuaJi2020ErFix1/css/popup.css
WuaiPojieLuntanjinghuaJi2020ErFix1/font/__init__.py
WuaiPojieLuntanjinghuaJi2020ErFix1/font/fontello.eot
WuaiPojieLuntanjinghuaJi2020ErFix1/font/fontello.svg
WuaiPojieLuntanjinghuaJi2020ErFix1/font/fontello.ttf
WuaiPojieLuntanjinghuaJi2020ErFix1/font/fontello.woff
WuaiPojieLuntanjinghuaJi2020ErFix1/img/__init__.py
WuaiPojieLuntanjinghuaJi2020ErFix1/img/annotator-glyph-sprite.png
WuaiPojieLuntanjinghuaJi2020ErFix1/img/annotator-icon-sprite.png
WuaiPojieLuntanjinghuaJi2020ErFix1/img/apple-touch-icon.png
WuaiPojieLuntanjinghuaJi2020ErFix1/img/cancelfullscreen.png
WuaiPojieLuntanjinghuaJi2020ErFix1/img/close.png
WuaiPojieLuntanjinghuaJi2020ErFix1/img/fullscreen.png
WuaiPojieLuntanjinghuaJi2020ErFix1/img/loader.gif
WuaiPojieLuntanjinghuaJi2020ErFix1/img/menu-icon.png
WuaiPojieLuntanjinghuaJi2020ErFix1/img/save.png
WuaiPojieLuntanjinghuaJi2020ErFix1/img/saved.png
WuaiPojieLuntanjinghuaJi2020ErFix1/img/settings-s.png
WuaiPojieLuntanjinghuaJi2020ErFix1/img/settings.png
WuaiPojieLuntanjinghuaJi2020ErFix1/img/star.png
WuaiPojieLuntanjinghuaJi2020ErFix1/js/__init__.py
WuaiPojieLuntanjinghuaJi2020ErFix1/js/epub.js
WuaiPojieLuntanjinghuaJi2020ErFix1/js/epub.min.js
WuaiPojieLuntanjinghuaJi2020ErFix1/js/epub.min.map
WuaiPojieLuntanjinghuaJi2020ErFix1/js/hooks.min.js
WuaiPojieLuntanjinghuaJi2020ErFix1/js/hooks.min.map
WuaiPojieLuntanjinghuaJi2020ErFix1/js/reader.js
WuaiPojieLuntanjinghuaJi2020ErFix1/js/reader.js.map
WuaiPojieLuntanjinghuaJi2020ErFix1/js/reader.min.js
wuai_pojie_luntanjinghua_ji_2020_er_fix1-2025.3.25.0.dist-info/METADATA
wuai_pojie_luntanjinghua_ji_2020_er_fix1-2025.3.25.0.dist-info/WHEEL
wuai_pojie_luntanjinghua_ji_2020_er_fix1-2025.3.25.0.dist-info/entry_points.txt
wuai_pojie_luntanjinghua_ji_2020_er_fix1-2025.3.25.0.dist-info/top_level.txt
wuai_pojie_luntanjinghua_ji_2020_er_fix1-2025.3.25.0.dist-info/RECORD
